kids4kars/__init__.py
kids4kars-1.0.0.dist-info/METADATA
kids4kars-1.0.0.dist-info/WHEEL
kids4kars-1.0.0.dist-info/top_level.txt
kids4kars-1.0.0.dist-info/RECORD
