Metadata-Version: 2.1
Name: kids4kars
Version: 1.0.0
Summary: the most useless python module.
Home-page: UNKNOWN
Author: detpik
License: UNKNOWN
Platform: any
